pySPFM/__about__.py
pySPFM/__init__.py
pySPFM/_utils.py
pySPFM/_version.py
pySPFM/base.py
pySPFM/decomposition.py
pySPFM/due.py
pySPFM/io.py
pySPFM/jobqueue.yaml
pySPFM/utils.py
pySPFM/_solvers/__init__.py
pySPFM/_solvers/debiasing.py
pySPFM/_solvers/fista.py
pySPFM/_solvers/hrf_generator.py
pySPFM/_solvers/lars.py
pySPFM/_solvers/select_lambda.py
pySPFM/_solvers/spatial_regularization.py
pySPFM/_solvers/stability_selection.py
pySPFM/cli/__init__.py
pySPFM/cli/_parser_utils.py
pySPFM/cli/_preprocessing.py
pySPFM/cli/auc_to_estimates.py
pySPFM/cli/run.py
pySPFM/tests/__init__.py
pySPFM/tests/conftest.py
pySPFM/tests/test_auc_to_estimates.py
pySPFM/tests/test_base.py
pySPFM/tests/test_cli.py
pySPFM/tests/test_debiasing.py
pySPFM/tests/test_decomposition.py
pySPFM/tests/test_fista.py
pySPFM/tests/test_hrf_generator.py
pySPFM/tests/test_integration.py
pySPFM/tests/test_io.py
pySPFM/tests/test_lars.py
pySPFM/tests/test_parser_utils.py
pySPFM/tests/test_preprocessing.py
pySPFM/tests/test_regressors.py
pySPFM/tests/test_select_lambda.py
pySPFM/tests/test_spatial_regularization.py
pySPFM/tests/test_stability_selection.py
pySPFM/tests/test_utils.py
pySPFM/tests/test_utils_coverage.py
pySPFM/tests/utils.py
pyspfm-2.0.2.dist-info/METADATA
pyspfm-2.0.2.dist-info/WHEEL
pyspfm-2.0.2.dist-info/entry_points.txt
pyspfm-2.0.2.dist-info/licenses/LICENSE
pyspfm-2.0.2.dist-info/RECORD
