Metadata-Version: 2.4
Name: pySPFM
Version: 2.0.2
Summary: Sparse hemodynamic deconvolution of fMRI data with scikit-learn compatible estimators.
Project-URL: Homepage, https://github.com/Paradigm-Free-Mapping/pySPFM
Project-URL: Documentation, https://pySPFM.readthedocs.io
Project-URL: Repository, https://github.com/Paradigm-Free-Mapping/pySPFM
Project-URL: Changelog, https://github.com/Paradigm-Free-Mapping/pySPFM/blob/main/CHANGELOG.md
Author: Eneko Uruñuela
License:                   GNU LESSER GENERAL PUBLIC LICENSE
License-File: LICENSE
Keywords: deconvolution,fmri,hemodynamic,neuroimaging,paradigm-free-mapping,sparse
Classifier: Development Status :: 4 - Beta
Classifier: Intended Audience :: Science/Research
Classifier: License :: OSI Approved :: GNU Library or Lesser General Public License (LGPL)
Classifier: Programming Language :: Python :: 3.10
Classifier: Programming Language :: Python :: 3.11
Classifier: Programming Language :: Python :: 3.12
Classifier: Topic :: Scientific/Engineering :: Information Analysis
Classifier: Topic :: Scientific/Engineering :: Medical Science Apps.
Requires-Python: >=3.10
Requires-Dist: dask
Requires-Dist: dask-jobqueue
Requires-Dist: distributed
Requires-Dist: jax
Requires-Dist: jaxlib
Requires-Dist: nibabel
Requires-Dist: nilearn>=0.10.0
Requires-Dist: numpy>=1.22
Requires-Dist: pylops>=1.18.2
Requires-Dist: pyproximal>=0.4.0
Requires-Dist: pywavelets
Requires-Dist: scipy>=1.9.0
Provides-Extra: all
Requires-Dist: codecov; extra == 'all'
Requires-Dist: coverage; extra == 'all'
Requires-Dist: ipykernel; extra == 'all'
Requires-Dist: matplotlib; extra == 'all'
Requires-Dist: myst-nb; extra == 'all'
Requires-Dist: pre-commit; extra == 'all'
Requires-Dist: pytest; extra == 'all'
Requires-Dist: pytest-console-scripts; extra == 'all'
Requires-Dist: pytest-cov>=4.0.0; extra == 'all'
Requires-Dist: requests; extra == 'all'
Requires-Dist: ruff>=0.4.0; extra == 'all'
Requires-Dist: sphinx; extra == 'all'
Requires-Dist: sphinx-argparse; extra == 'all'
Requires-Dist: sphinx-book-theme; extra == 'all'
Requires-Dist: sphinx-charts; extra == 'all'
Requires-Dist: sphinx-copybutton; extra == 'all'
Requires-Dist: sphinx-design; extra == 'all'
Requires-Dist: sphinx-gallery; extra == 'all'
Requires-Dist: sphinx-rtd-theme>=1.2.2; extra == 'all'
Requires-Dist: sphinxcontrib-bibtex; extra == 'all'
Requires-Dist: sphinxcontrib-jquery; extra == 'all'
Provides-Extra: dev
Requires-Dist: pre-commit; extra == 'dev'
Provides-Extra: doc
Requires-Dist: ipykernel; extra == 'doc'
Requires-Dist: matplotlib; extra == 'doc'
Requires-Dist: myst-nb; extra == 'doc'
Requires-Dist: sphinx; extra == 'doc'
Requires-Dist: sphinx-argparse; extra == 'doc'
Requires-Dist: sphinx-book-theme; extra == 'doc'
Requires-Dist: sphinx-charts; extra == 'doc'
Requires-Dist: sphinx-copybutton; extra == 'doc'
Requires-Dist: sphinx-design; extra == 'doc'
Requires-Dist: sphinx-gallery; extra == 'doc'
Requires-Dist: sphinx-rtd-theme>=1.2.2; extra == 'doc'
Requires-Dist: sphinxcontrib-bibtex; extra == 'doc'
Requires-Dist: sphinxcontrib-jquery; extra == 'doc'
Provides-Extra: tests
Requires-Dist: codecov; extra == 'tests'
Requires-Dist: coverage; extra == 'tests'
Requires-Dist: pytest; extra == 'tests'
Requires-Dist: pytest-console-scripts; extra == 'tests'
Requires-Dist: pytest-cov>=4.0.0; extra == 'tests'
Requires-Dist: requests; extra == 'tests'
Requires-Dist: ruff>=0.4.0; extra == 'tests'
